[{"id":"ckyuh7chc00014twe7f583gsk","createdAt":"2022-01-25T18:52:42.864Z","updatedAt":"2022-01-25T18:52:42.864Z","postId":"ckyuh7cha00004twe4qri2i03","userId":"4"},{"id":"ckyuh7chc00024twe6nyzfoty","createdAt":"2022-01-25T18:52:42.864Z","updatedAt":"2022-01-25T18:52:42.864Z","postId":"ckyuh7cha00004twe4qri2i03","userId":"1"},{"id":"ckyuh7chd00034tweejcz2y97","createdAt":"2022-01-25T18:52:42.865Z","updatedAt":"2022-01-25T18:52:42.865Z","postId":"ckyuh7cha00004twe4qri2i03","userId":"2"},{"id":"ckyuh7chg00054twe3qfg41gb","createdAt":"2022-01-25T18:52:42.869Z","updatedAt":"2022-01-25T18:52:42.869Z","postId":"ckyuh7chg00044twe8ofvgcut","userId":"3"},{"id":"ckyuh7chh00064twea7xi2eqe","createdAt":"2022-01-25T18:52:42.869Z","updatedAt":"2022-01-25T18:52:42.869Z","postId":"ckyuh7chg00044twe8ofvgcut","userId":"5"},{"id":"ckyuh7chh00074twe0tegg82b","createdAt":"2022-01-25T18:52:42.869Z","updatedAt":"2022-01-25T18:52:42.869Z","postId":"ckyuh7chg00044twe8ofvgcut","userId":"2"},{"id":"ckyuh7chi00084twe2kau6hge","createdAt":"2022-01-25T18:52:42.870Z","updatedAt":"2022-01-25T18:52:42.870Z","postId":"ckyuh7chg00044twe8ofvgcut","userId":"1"},{"id":"ckyuh7chj000a4twe5hfge04d","createdAt":"2022-01-25T18:52:42.871Z","updatedAt":"2022-01-25T18:52:42.871Z","postId":"ckyuh7chj00094twe33eu3tsf","userId":"1"},{"id":"ckyuh7chj000b4twehfgn4i8m","createdAt":"2022-01-25T18:52:42.871Z","updatedAt":"2022-01-25T18:52:42.871Z","postId":"ckyuh7chj00094twe33eu3tsf","userId":"3"},{"id":"ckyuh7chk000c4twe3kenf3yi","createdAt":"2022-01-25T18:52:42.872Z","updatedAt":"2022-01-25T18:52:42.872Z","postId":"ckyuh7chj00094twe33eu3tsf","userId":"4"},{"id":"ckyuh7chk000d4twedf9reqb8","createdAt":"2022-01-25T18:52:42.872Z","updatedAt":"2022-01-25T18:52:42.872Z","postId":"ckyuh7chj00094twe33eu3tsf","userId":"5"},{"id":"ckyuh7chk000e4tweg2u1fgm1","createdAt":"2022-01-25T18:52:42.872Z","updatedAt":"2022-01-25T18:52:42.872Z","postId":"ckyuh7chj00094twe33eu3tsf","userId":"2"},{"id":"ckyuh7chl000g4twe3fgs5g69","createdAt":"2022-01-25T18:52:42.873Z","updatedAt":"2022-01-25T18:52:42.873Z","postId":"ckyuh7chl000f4twebll04ucv","userId":"2"},{"id":"ckyuh7chl000h4twecjx4h2vs","createdAt":"2022-01-25T18:52:42.873Z","updatedAt":"2022-01-25T18:52:42.873Z","postId":"ckyuh7chl000f4twebll04ucv","userId":"5"},{"id":"ckyuh7chl000i4twegwfieeg1","createdAt":"2022-01-25T18:52:42.873Z","updatedAt":"2022-01-25T18:52:42.873Z","postId":"ckyuh7chl000f4twebll04ucv","userId":"4"},{"id":"ckyuh7chm000j4twee76n2ecf","createdAt":"2022-01-25T18:52:42.874Z","updatedAt":"2022-01-25T18:52:42.874Z","postId":"ckyuh7chl000f4twebll04ucv","userId":"3"},{"id":"ckyuh7chm000k4twe3waadp9g","createdAt":"2022-01-25T18:52:42.874Z","updatedAt":"2022-01-25T18:52:42.874Z","postId":"ckyuh7chl000f4twebll04ucv","userId":"1"},{"id":"ckyuh7chm000m4twe019cekjm","createdAt":"2022-01-25T18:52:42.874Z","updatedAt":"2022-01-25T18:52:42.874Z","postId":"ckyuh7chm000l4twe6d5rdkk9","userId":"2"},{"id":"ckyuh7chn000n4twe79ua8qfq","createdAt":"2022-01-25T18:52:42.875Z","updatedAt":"2022-01-25T18:52:42.875Z","postId":"ckyuh7chm000l4twe6d5rdkk9","userId":"5"},{"id":"ckyuh7chn000o4twe0pup1w98","createdAt":"2022-01-25T18:52:42.875Z","updatedAt":"2022-01-25T18:52:42.875Z","postId":"ckyuh7chm000l4twe6d5rdkk9","userId":"4"},{"id":"ckyuh7cho000q4twecbbgggdj","createdAt":"2022-01-25T18:52:42.876Z","updatedAt":"2022-01-25T18:52:42.876Z","postId":"ckyuh7cho000p4tweckca490i","userId":"2"},{"id":"ckyuh7cho000r4twegcvnhgpe","createdAt":"2022-01-25T18:52:42.876Z","updatedAt":"2022-01-25T18:52:42.876Z","postId":"ckyuh7cho000p4tweckca490i","userId":"5"},{"id":"ckyuh7chp000t4twegnhnehkc","createdAt":"2022-01-25T18:52:42.877Z","updatedAt":"2022-01-25T18:52:42.877Z","postId":"ckyuh7chp000s4twebyms1ar0","userId":"5"},{"id":"ckyuh7chp000u4twe1v3d2199","createdAt":"2022-01-25T18:52:42.877Z","updatedAt":"2022-01-25T18:52:42.877Z","postId":"ckyuh7chp000s4twebyms1ar0","userId":"2"},{"id":"ckyuh7chq000v4twefe59es8y","createdAt":"2022-01-25T18:52:42.878Z","updatedAt":"2022-01-25T18:52:42.878Z","postId":"ckyuh7chp000s4twebyms1ar0","userId":"3"},{"id":"ckyuh7chq000w4twee66q7bvv","createdAt":"2022-01-25T18:52:42.878Z","updatedAt":"2022-01-25T18:52:42.878Z","postId":"ckyuh7chp000s4twebyms1ar0","userId":"1"},{"id":"ckyuh7chr000y4twe2wyr7xk9","createdAt":"2022-01-25T18:52:42.879Z","updatedAt":"2022-01-25T18:52:42.879Z","postId":"ckyuh7chq000x4twebp7z6e4k","userId":"3"},{"id":"ckyuh7chr000z4twegjq37urs","createdAt":"2022-01-25T18:52:42.879Z","updatedAt":"2022-01-25T18:52:42.879Z","postId":"ckyuh7chq000x4twebp7z6e4k","userId":"2"},{"id":"ckyuh7chr00104twe45weamji","createdAt":"2022-01-25T18:52:42.879Z","updatedAt":"2022-01-25T18:52:42.879Z","postId":"ckyuh7chq000x4twebp7z6e4k","userId":"1"},{"id":"ckyuh7chs00114twea47uba0q","createdAt":"2022-01-25T18:52:42.880Z","updatedAt":"2022-01-25T18:52:42.880Z","postId":"ckyuh7chq000x4twebp7z6e4k","userId":"4"},{"id":"ckyuh7cht00134tweggwd8de9","createdAt":"2022-01-25T18:52:42.881Z","updatedAt":"2022-01-25T18:52:42.881Z","postId":"ckyuh7chs00124twe4m29emdd","userId":"5"},{"id":"ckyuh7cht00144twe23iv62od","createdAt":"2022-01-25T18:52:42.881Z","updatedAt":"2022-01-25T18:52:42.881Z","postId":"ckyuh7chs00124twe4m29emdd","userId":"4"},{"id":"ckyuh7cht00164twedx1n0hhe","createdAt":"2022-01-25T18:52:42.881Z","updatedAt":"2022-01-25T18:52:42.881Z","postId":"ckyuh7cht00154twefyl4evvi","userId":"3"},{"id":"ckyuh7chu00174twe2mch0bt4","createdAt":"2022-01-25T18:52:42.882Z","updatedAt":"2022-01-25T18:52:42.882Z","postId":"ckyuh7cht00154twefyl4evvi","userId":"5"},{"id":"ckyuh7chu00194twebnh1bq8x","createdAt":"2022-01-25T18:52:42.882Z","updatedAt":"2022-01-25T18:52:42.882Z","postId":"ckyuh7chu00184twe9i1gdws6","userId":"4"},{"id":"ckyuh7chv001a4twe80p5bnhw","createdAt":"2022-01-25T18:52:42.883Z","updatedAt":"2022-01-25T18:52:42.883Z","postId":"ckyuh7chu00184twe9i1gdws6","userId":"5"},{"id":"ckyuh7chv001b4tweewee9ooe","createdAt":"2022-01-25T18:52:42.883Z","updatedAt":"2022-01-25T18:52:42.883Z","postId":"ckyuh7chu00184twe9i1gdws6","userId":"1"},{"id":"ckyuh7chw001d4twe1mmqfpx8","createdAt":"2022-01-25T18:52:42.884Z","updatedAt":"2022-01-25T18:52:42.884Z","postId":"ckyuh7chv001c4tweffowfjv9","userId":"3"},{"id":"ckyuh7chw001e4twee6cwh2ts","createdAt":"2022-01-25T18:52:42.884Z","updatedAt":"2022-01-25T18:52:42.884Z","postId":"ckyuh7chv001c4tweffowfjv9","userId":"1"},{"id":"ckyuh7chw001f4twecl3n83v9","createdAt":"2022-01-25T18:52:42.884Z","updatedAt":"2022-01-25T18:52:42.884Z","postId":"ckyuh7chv001c4tweffowfjv9","userId":"5"},{"id":"ckyuh7chx001h4tweh5fj9417","createdAt":"2022-01-25T18:52:42.885Z","updatedAt":"2022-01-25T18:52:42.885Z","postId":"ckyuh7chx001g4twe2qzwhaqg","userId":"2"},{"id":"ckyuh7chx001i4twea26h2mfc","createdAt":"2022-01-25T18:52:42.885Z","updatedAt":"2022-01-25T18:52:42.885Z","postId":"ckyuh7chx001g4twe2qzwhaqg","userId":"4"},{"id":"ckyuh7chy001k4twe68jug9sq","createdAt":"2022-01-25T18:52:42.886Z","updatedAt":"2022-01-25T18:52:42.886Z","postId":"ckyuh7chx001j4twe4f8w52nd","userId":"2"},{"id":"ckyuh7chy001l4tweeq0vds24","createdAt":"2022-01-25T18:52:42.886Z","updatedAt":"2022-01-25T18:52:42.886Z","postId":"ckyuh7chx001j4twe4f8w52nd","userId":"4"},{"id":"ckyuh7chz001n4twegyrv4ca9","createdAt":"2022-01-25T18:52:42.887Z","updatedAt":"2022-01-25T18:52:42.887Z","postId":"ckyuh7chy001m4twe5lqw4s83","userId":"5"},{"id":"ckyuh7chz001o4twe7g6a10pt","createdAt":"2022-01-25T18:52:42.887Z","updatedAt":"2022-01-25T18:52:42.887Z","postId":"ckyuh7chy001m4twe5lqw4s83","userId":"3"},{"id":"ckyuh7ci0001q4twegqp57c90","createdAt":"2022-01-25T18:52:42.888Z","updatedAt":"2022-01-25T18:52:42.888Z","postId":"ckyuh7chz001p4twe9epacjr3","userId":"1"},{"id":"ckyuh7ci0001r4twecswd0ckr","createdAt":"2022-01-25T18:52:42.888Z","updatedAt":"2022-01-25T18:52:42.888Z","postId":"ckyuh7chz001p4twe9epacjr3","userId":"4"},{"id":"ckyuh7ci0001t4twe1l18fbqd","createdAt":"2022-01-25T18:52:42.888Z","updatedAt":"2022-01-25T18:52:42.888Z","postId":"ckyuh7ci0001s4twecgt11umw","userId":"2"},{"id":"ckyuh7ci1001u4twe4b7d4xaj","createdAt":"2022-01-25T18:52:42.889Z","updatedAt":"2022-01-25T18:52:42.889Z","postId":"ckyuh7ci0001s4twecgt11umw","userId":"1"},{"id":"ckyuh7ci1001v4twec27sg809","createdAt":"2022-01-25T18:52:42.889Z","updatedAt":"2022-01-25T18:52:42.889Z","postId":"ckyuh7ci0001s4twecgt11umw","userId":"4"},{"id":"ckyuh7ci1001w4twe0951dk4g","createdAt":"2022-01-25T18:52:42.889Z","updatedAt":"2022-01-25T18:52:42.889Z","postId":"ckyuh7ci0001s4twecgt11umw","userId":"3"},{"id":"ckyuh7ci2001y4twebxkm30bk","createdAt":"2022-01-25T18:52:42.890Z","updatedAt":"2022-01-25T18:52:42.890Z","postId":"ckyuh7ci2001x4twe0vz45bdk","userId":"2"},{"id":"ckyuh7ci2001z4twed12i7di0","createdAt":"2022-01-25T18:52:42.890Z","updatedAt":"2022-01-25T18:52:42.890Z","postId":"ckyuh7ci2001x4twe0vz45bdk","userId":"1"},{"id":"ckyuh7ci200204twech4636yb","createdAt":"2022-01-25T18:52:42.890Z","updatedAt":"2022-01-25T18:52:42.890Z","postId":"ckyuh7ci2001x4twe0vz45bdk","userId":"5"},{"id":"ckyuh7ci300224twe5jjiah0n","createdAt":"2022-01-25T18:52:42.891Z","updatedAt":"2022-01-25T18:52:42.891Z","postId":"ckyuh7ci300214twe7lu3ctlk","userId":"4"},{"id":"ckyuh7ci300234tweeolh8iqt","createdAt":"2022-01-25T18:52:42.891Z","updatedAt":"2022-01-25T18:52:42.891Z","postId":"ckyuh7ci300214twe7lu3ctlk","userId":"5"},{"id":"ckyuh7ci400254twe7bqeb6ac","createdAt":"2022-01-25T18:52:42.892Z","updatedAt":"2022-01-25T18:52:42.892Z","postId":"ckyuh7ci300244twe8pj78mbk","userId":"3"},{"id":"ckyuh7ci400264twee3tw9xew","createdAt":"2022-01-25T18:52:42.892Z","updatedAt":"2022-01-25T18:52:42.892Z","postId":"ckyuh7ci300244twe8pj78mbk","userId":"4"},{"id":"ckyuh7ci400274twe7o9lfvnm","createdAt":"2022-01-25T18:52:42.892Z","updatedAt":"2022-01-25T18:52:42.892Z","postId":"ckyuh7ci300244twe8pj78mbk","userId":"2"},{"id":"ckyuh7ci400284twebx3oa3mu","createdAt":"2022-01-25T18:52:42.892Z","updatedAt":"2022-01-25T18:52:42.892Z","postId":"ckyuh7ci300244twe8pj78mbk","userId":"5"},{"id":"ckyuh7ci5002a4twe9vmi1612","createdAt":"2022-01-25T18:52:42.893Z","updatedAt":"2022-01-25T18:52:42.893Z","postId":"ckyuh7ci500294twebwa3apat","userId":"3"},{"id":"ckyuh7ci5002b4tweafy43k5z","createdAt":"2022-01-25T18:52:42.893Z","updatedAt":"2022-01-25T18:52:42.893Z","postId":"ckyuh7ci500294twebwa3apat","userId":"2"},{"id":"ckyuh7ci6002c4twe701ecmac","createdAt":"2022-01-25T18:52:42.894Z","updatedAt":"2022-01-25T18:52:42.894Z","postId":"ckyuh7ci500294twebwa3apat","userId":"5"},{"id":"ckyuh7ci6002d4tweeiy2bmft","createdAt":"2022-01-25T18:52:42.894Z","updatedAt":"2022-01-25T18:52:42.894Z","postId":"ckyuh7ci500294twebwa3apat","userId":"4"},{"id":"ckyuh7ci7002f4twe28ypfrsp","createdAt":"2022-01-25T18:52:42.895Z","updatedAt":"2022-01-25T18:52:42.895Z","postId":"ckyuh7ci7002e4twe66189bvy","userId":"3"},{"id":"ckyuh7ci8002g4twe6sx11sjo","createdAt":"2022-01-25T18:52:42.896Z","updatedAt":"2022-01-25T18:52:42.896Z","postId":"ckyuh7ci7002e4twe66189bvy","userId":"5"}]